[
 {
  "docstatus": 0,
  "doctype": "intergrated systems child",
  "end_points": null,
  "modified": "2025-01-06 10:53:14.113404",
  "name": "krffobb601",
  "other_requirments": null,
  "parent": "register procsess",
  "parentfield": "table_guga",
  "parenttype": "Master Processes",
  "system_name": "google (Oauth)"
 },
 {
  "docstatus": 0,
  "doctype": "intergrated systems child",
  "end_points": null,
  "modified": "2025-01-06 10:53:14.575908",
  "name": "04c3sbpp61",
  "other_requirments": null,
  "parent": "login",
  "parentfield": "table_guga",
  "parenttype": "Master Processes",
  "system_name": "google(oauth)"
 }
]